rtl/shift_reg.v
`timescale 1ns / 1ps
//////////////////////////////////////////////////////////////////////////////////
// Company: 
// Engineer: 
// 
// Create Date: 04.02.2026 18:10:51
// Design Name: 
// Module Name: shift_reg
// Project Name: 
// Target Devices: 
// Tool Versions: 
// Description: 
// 
// Dependencies: 
// 
// Revision:
// Revision 0.01 - File Created
// Additional Comments:
// 
//////////////////////////////////////////////////////////////////////////////////


// Description : SPI shift register - transmit (MOSI) and receive (MISO)
//               Supports all 4 SPI modes (cpol/cpha) and LSB/MSB first.
module shift_reg(
    input            PCLK,
    input            PRESET_n,
    input            ss_i,               // 1 = deasserted, 0 = active/asserted
    input            send_data_i,
    input            lsbfe_i,            // 1 = LSB first, 0 = MSB first
    input            cpha_i,
    input            cpol_i,
    input            miso_receive_sclk_i,
    input            miso_receive_sclk0_i,
    input            mosi_send_sclk_i,
    input            mosi_send_sclk0_i,
    input  [7:0]     data_mosi_i,
    input            miso_i,
    input            receive_data_i,
 
    output reg       mosi_o,
    output     [7:0] data_miso_o
);
    reg [7:0] shift_register;   // transmit holding register
    reg [7:0] temp_reg;         // received-data latch (shown to APB)
    reg [7:0] temp;             // bit-by-bit MISO assembly register
    reg [2:0] count,  count1;   // MOSI bit indices  (LSB-first / MSB-first)
    reg [2:0] count2, count3;   // MISO bit indices  (LSB-first / MSB-first)
 
    // clk_wire selects which sclk edge the block responds to
    // Image diagrams: cpha ^ cpol selects the active clock path
    wire clk_wire;
    assign clk_wire = (cpha_i ^ cpol_i);   // 1 → use sclk, 0 → use sclk0
 
    // -----------------------------------------------------------------------
    // Transmit holding register (shift_register) - Image 2 left block
    //   Reset  → 8'b0
    //   send_data=1 → load data_mosi_i
    //   else → hold
    // -----------------------------------------------------------------------
    always @(posedge PCLK or negedge PRESET_n) begin
        if (!PRESET_n)
            shift_register <= 8'd0;
        else if (send_data_i)
            shift_register <= data_mosi_i;
    end
 
    // -----------------------------------------------------------------------
    // Received-data latch (temp_reg) - Image 2 right mux/FF
    //   receive_data=1 → latch temp into temp_reg
    // -----------------------------------------------------------------------
    always @(posedge PCLK or negedge PRESET_n) begin
        if (!PRESET_n)
            temp_reg <= 8'h00;
        else if (receive_data_i)
            temp_reg <= temp;
    end
 
    // data_miso_o: 0 when receive_data inactive, temp_reg otherwise
    assign data_miso_o = receive_data_i ? temp_reg : 8'h00;
 
    // -----------------------------------------------------------------------
    // MOSI bit counter - count (LSB-first) / count1 (MSB-first) 
    //   Reset / ss deasserted → count=0, count1=7
    //   clk_wire=1 & mosi_send_sclk_i  → increment/decrement
    //   clk_wire=0 & mosi_send_sclk0_i → increment/decrement
    // -----------------------------------------------------------------------
    always @(posedge PCLK or negedge PRESET_n) begin
        if (!PRESET_n) begin
            count  <= 3'd0;
            count1 <= 3'd7;
        end
        else if (ss_i) begin          
            count  <= count;
            count1 <= count1;
        end
        else begin                    // ss active (!ss_i)
            if (clk_wire && mosi_send_sclk_i) begin
                if (lsbfe_i)
                    count  <= (count  == 3'd7) ? 3'd0 : count  + 1'b1;
                else
                    count1 <= (count1 == 3'd0) ? 3'd7 : count1 - 1'b1;
            end
            else if (!clk_wire && mosi_send_sclk0_i) begin
                if (lsbfe_i)
                    count  <= (count  == 3'd7) ? 3'd0 : count  + 1'b1;
                else
                    count1 <= (count1 == 3'd0) ? 3'd7 : count1 - 1'b1;
            end
        end
    end
 
    // -----------------------------------------------------------------------
    // MISO bit counter - count2 (LSB-first) / count3 (MSB-first) 
    //   Mirror of MOSI counter but driven by miso_receive_sclk edges
    //   clk_wire=1 → sample on sclk0 edge (miso_receive_sclk0_i)
    //   clk_wire=0 → sample on sclk  edge (miso_receive_sclk_i)
    // -----------------------------------------------------------------------
    always @(posedge PCLK or negedge PRESET_n) begin
        if (!PRESET_n) begin
            count2 <= 3'd0;
            count3 <= 3'd7;
        end
        else if (ss_i) begin
            count2 <= 3'd0;
            count3 <= 3'd7;
        end
        else begin
            if ((clk_wire && miso_receive_sclk0_i) || (!clk_wire && miso_receive_sclk_i)) begin
                if (lsbfe_i)
                    count2 <= (count2 == 3'd7) ? 3'd0 : count2 + 1'b1;
                else
                    count3 <= (count3 == 3'd0) ? 3'd7 : count3 - 1'b1;
            end
        end
    end
 
    // -----------------------------------------------------------------------
    // MISO sample/assemble into temp 
    // -----------------------------------------------------------------------
    wire miso_sample_en;
    assign miso_sample_en = (clk_wire  && miso_receive_sclk0_i) ||
                            (!clk_wire && miso_receive_sclk_i);
 
    always @(posedge PCLK or negedge PRESET_n) begin
        if (!PRESET_n)
            temp <= 8'h00;
        else if (!ss_i && miso_sample_en) begin
            if (lsbfe_i)
                temp[count2] <= miso_i;
            else
                temp[count3] <= miso_i;
        end
    end
 
    // -----------------------------------------------------------------------
    //   Reset / ss deasserted → 1'b0
    //   Active: drive shift_register[count] (LSB-first) or [count1] (MSB-first)
    //   on the appropriate sclk edge
    // -----------------------------------------------------------------------
    always @(posedge PCLK or negedge PRESET_n) begin
        if (!PRESET_n)
            mosi_o <= 1'b0;
        else if (ss_i)
            mosi_o <= 1'b0;      // ss deasserted → MOSI idle low
        else begin               // ss active
            if (clk_wire && mosi_send_sclk_i)
                mosi_o <= lsbfe_i ? shift_register[count] : shift_register[count1];
            else if (!clk_wire && mosi_send_sclk0_i)
                mosi_o <= lsbfe_i ? shift_register[count] : shift_register[count1];
            // else: hold MOSI between edges
        end
    end
 
endmodule

tb/shift_reg_tb.v
`timescale 1ns / 1ps
//////////////////////////////////////////////////////////////////////////////////
// Company: 
// Engineer: 
// 
// Create Date: 05.02.2026 07:22:59
// Design Name: 
// Module Name: shift_reg_tb
// Project Name: 
// Target Devices: 
// Tool Versions: 
// Description: 
// 
// Dependencies: 
// 
// Revision:
// Revision 0.01 - File Created
// Additional Comments:
// 
//////////////////////////////////////////////////////////////////////////////////

// Tests     : MSB-first TX, LSB-first TX, MSB-first RX, LSB-first RX,
//             all 4 SPI modes (cpol/cpha), reset mid-frame

module shift_reg_tb();
 
    // -----------------------------------------------------------------------
    // DUT ports
    // -----------------------------------------------------------------------
    reg         PCLK;
    reg         PRESET_n;
    reg         ss_i;
    reg         send_data_i;
    reg         lsbfe_i;
    reg         cpha_i;
    reg         cpol_i;
    reg         miso_receive_sclk_i;
    reg         miso_receive_sclk0_i;
    reg         mosi_send_sclk_i;
    reg         mosi_send_sclk0_i;
    reg  [7:0]  data_mosi_i;
    reg         miso_i;
    reg         receive_data_i;
 
    wire        mosi_o;
    wire [7:0]  data_miso_o;
 
    // variable to capture data_miso_o while receive_data_i is still high
    reg  [7:0]  captured_miso;
 
    // -----------------------------------------------------------------------
    // DUT instantiation
    // -----------------------------------------------------------------------
    shift_reg dut (
        .PCLK                (PCLK),
        .PRESET_n            (PRESET_n),
        .ss_i                (ss_i),
        .send_data_i         (send_data_i),
        .lsbfe_i             (lsbfe_i),
        .cpha_i              (cpha_i),
        .cpol_i              (cpol_i),
        .miso_receive_sclk_i (miso_receive_sclk_i),
        .miso_receive_sclk0_i(miso_receive_sclk0_i),
        .mosi_send_sclk_i    (mosi_send_sclk_i),
        .mosi_send_sclk0_i   (mosi_send_sclk0_i),
        .data_mosi_i         (data_mosi_i),
        .miso_i              (miso_i),
        .receive_data_i      (receive_data_i),
        .mosi_o              (mosi_o),
        .data_miso_o         (data_miso_o)
    );
 
    // -----------------------------------------------------------------------
    // Clock (10 ns period)
    // -----------------------------------------------------------------------
    initial PCLK = 0;
    always  #5 PCLK = ~PCLK;
 
    // -----------------------------------------------------------------------
    // clk_sel: cpha ^ cpol
    //   1 → MOSI/MISO on sclk_i path
    //   0 → MOSI/MISO on sclk0_i path
    // -----------------------------------------------------------------------
    function clk_sel;
        input dummy;
        clk_sel = cpha_i ^ cpol_i;
    endfunction
 
    // -----------------------------------------------------------------------
    // Task: apply_reset
    // -----------------------------------------------------------------------
    task apply_reset;
        begin
            PRESET_n             = 1'b0;
            ss_i                 = 1'b1;
            send_data_i          = 1'b0;
            receive_data_i       = 1'b0;
            miso_receive_sclk_i  = 1'b0;
            miso_receive_sclk0_i = 1'b0;
            mosi_send_sclk_i     = 1'b0;
            mosi_send_sclk0_i    = 1'b0;
            miso_i               = 1'b0;
            data_mosi_i          = 8'h00;
            repeat (3) @(posedge PCLK);
            @(negedge PCLK);
            PRESET_n = 1'b1;
            $display("[%0t] RESET released", $time);
        end
    endtask
 
    // -----------------------------------------------------------------------
    // Task: load_mosi
    // -----------------------------------------------------------------------
    task load_mosi;
        input [7:0] data;
        begin
            @(negedge PCLK);
            send_data_i = 1'b1;
            data_mosi_i = data;
            @(negedge PCLK);
            send_data_i = 1'b0;
            $display("[%0t] Loaded MOSI data = 0x%0h", $time, data);
        end
    endtask
 
    // -----------------------------------------------------------------------
    // Task: start_spi
    // -----------------------------------------------------------------------
    task start_spi;
        begin
            @(negedge PCLK);
            ss_i = 1'b0;
            $display("[%0t] SPI started (ss_i=0)", $time);
        end
    endtask
 
    // -----------------------------------------------------------------------
    // Task: stop_spi
    // -----------------------------------------------------------------------
    task stop_spi;
        begin
            @(negedge PCLK);
            ss_i = 1'b1;
            $display("[%0t] SPI stopped (ss_i=1)", $time);
        end
    endtask
 
    // -----------------------------------------------------------------------
    // Task: send_mosi_bit  (mode-aware sclk selection)
    // -----------------------------------------------------------------------
    task send_mosi_bit;
        begin
            @(negedge PCLK);
            if (clk_sel(0)) begin
                mosi_send_sclk_i  = 1'b1;
                @(negedge PCLK);
                mosi_send_sclk_i  = 1'b0;
            end else begin
                mosi_send_sclk0_i = 1'b1;
                @(negedge PCLK);
                mosi_send_sclk0_i = 1'b0;
            end
        end
    endtask
 
    // -----------------------------------------------------------------------
    // Task: receive_miso_bit  (mode-aware sclk selection)
    //   clk_wire=1 → MISO sampled on sclk0 edge
    //   clk_wire=0 → MISO sampled on sclk  edge
    // -----------------------------------------------------------------------
    task receive_miso_bit;
        input bit_val;
        begin
            @(negedge PCLK);
            miso_i = bit_val;
            if (clk_sel(0)) begin
                miso_receive_sclk0_i = 1'b1;
                @(negedge PCLK);
                miso_receive_sclk0_i = 1'b0;
            end else begin
                miso_receive_sclk_i  = 1'b1;
                @(negedge PCLK);
                miso_receive_sclk_i  = 1'b0;
            end
        end
    endtask
 
    // -----------------------------------------------------------------------
    // Task: read_received_data
    //   FIX: capture data_miso_o WHILE receive_data_i is still high,
    //        before the output mux returns it to 8'h00
    // -----------------------------------------------------------------------
    task read_received_data;
        begin
            @(negedge PCLK);
            receive_data_i = 1'b1;
            @(negedge PCLK);
            // Sample here - receive_data_i still 1, so mux selects temp_reg
            captured_miso  = data_miso_o;
            receive_data_i = 1'b0;
            $display("[%0t] read_received_data: captured = 0x%0h", $time, captured_miso);
        end
    endtask
 
    // -----------------------------------------------------------------------
    // Task: send_8_bits  - transmit full byte, display captured MOSI bits
    // -----------------------------------------------------------------------
    task send_8_bits;
        input [7:0] data;
        reg   [7:0] captured_bits;
        integer i;
        begin
            load_mosi(data);
            start_spi;
            captured_bits = 8'h00;
            for (i = 0; i < 8; i = i + 1) begin
                send_mosi_bit;
                captured_bits[i] = mosi_o;
            end
            $display("[%0t] TX done: sent=0x%0h mosi_bits=%b lsbfe=%b",
                     $time, data, captured_bits, lsbfe_i);
            stop_spi;
        end
    endtask
 
    // -----------------------------------------------------------------------
    // Task: receive_8_bits  - receive full byte, PASS/FAIL check
    //   rx_pattern: the byte whose bits are fed MSB-first in time
    //   expected  : the byte that should appear in data_miso_o
    // -----------------------------------------------------------------------
    task receive_8_bits;
        input [7:0] rx_pattern;
        input [7:0] expected;
        integer i;
        begin
            start_spi;
            for (i = 7; i >= 0; i = i - 1)
                receive_miso_bit(rx_pattern[i]);
            read_received_data;
            // Check captured_miso (sampled while receive_data_i was high)
            if (captured_miso === expected)
                $display("[%0t] PASS: data_miso_o=0x%0h (expected 0x%0h)",
                         $time, captured_miso, expected);
            else
                $display("[%0t] FAIL: data_miso_o=0x%0h (expected 0x%0h)",
                         $time, captured_miso, expected);
            stop_spi;
        end
    endtask
 
    // -----------------------------------------------------------------------
    // Task: test_reset_mid_frame
    // -----------------------------------------------------------------------
    task test_reset_mid_frame;
        begin
            $display("[%0t] TEST: reset mid-frame", $time);
            load_mosi(8'hFF);
            start_spi;
            send_mosi_bit;
            send_mosi_bit;
            send_mosi_bit;
            // Assert reset mid-frame
            PRESET_n = 1'b0;
            repeat (3) @(posedge PCLK);
            @(negedge PCLK);
            PRESET_n = 1'b1;
            repeat (2) @(posedge PCLK);
            if (mosi_o === 1'b0)
                $display("[%0t] PASS: mosi_o=0 after mid-frame reset", $time);
            else
                $display("[%0t] FAIL: mosi_o should be 0 after reset, got %b", $time, mosi_o);
            ss_i = 1'b1;
        end
    endtask
 
    // -----------------------------------------------------------------------
    // Main stimulus
    // -----------------------------------------------------------------------
    initial begin
        $dumpfile("shift_reg_tb.vcd");
        $dumpvars(0, shift_reg_tb);
 
        // ===== Mode 0 (cpol=0,cpha=0) MSB-first TX =====
        $display("\n===== Mode 0 (cpol=0,cpha=0) MSB-first TX =====");
        cpol_i = 0; cpha_i = 0; lsbfe_i = 0;
        apply_reset;
        send_8_bits(8'hA5);
        #20;
 
        // ===== Mode 0 (cpol=0,cpha=0) LSB-first TX =====
        $display("\n===== Mode 0 (cpol=0,cpha=0) LSB-first TX =====");
        lsbfe_i = 1;
        apply_reset;
        send_8_bits(8'hA5);
        #20;
 
        // ===== Mode 0 MSB-first RX: expect 0xCC =====
        $display("\n===== Mode 0 MSB-first RX: expect 0xCC =====");
        cpol_i = 0; cpha_i = 0; lsbfe_i = 0;
        apply_reset;
        // 0xCC = 1100_1100 → feed MSB first: 1,1,0,0,1,1,0,0
        receive_8_bits(8'hCC, 8'hCC);
        #20;
 
        // ===== Mode 0 LSB-first RX =====
        // Feed 0xCC MSB-first in time → LSB-first RX places:
        //   time-bit0(=MSB=1) → temp[0], time-bit1(=1) → temp[1], ...
        //   0xCC fed [7..0] = 1,1,0,0,1,1,0,0 → temp = 0011_0011 = 0x33
        $display("\n===== Mode 0 LSB-first RX: feed 0xCC MSB-first, expect 0x33 =====");
        lsbfe_i = 1;
        apply_reset;
        receive_8_bits(8'hCC, 8'h33);
        #20;
 
        // ===== Mode 1 (cpol=0,cpha=1) MSB-first TX =====
        $display("\n===== Mode 1 (cpol=0,cpha=1) MSB-first TX =====");
        cpol_i = 0; cpha_i = 1; lsbfe_i = 0;
        apply_reset;
        send_8_bits(8'h5A);
        #20;
 
        // ===== Mode 2 (cpol=1,cpha=0) MSB-first TX =====
        $display("\n===== Mode 2 (cpol=1,cpha=0) MSB-first TX =====");
        cpol_i = 1; cpha_i = 0; lsbfe_i = 0;
        apply_reset;
        send_8_bits(8'h5A);
        #20;
 
        // ===== Mode 3 (cpol=1,cpha=1) MSB-first TX =====
        $display("\n===== Mode 3 (cpol=1,cpha=1) MSB-first TX =====");
        cpol_i = 1; cpha_i = 1; lsbfe_i = 0;
        apply_reset;
        send_8_bits(8'h5A);
        #20;
 
        // ===== Mid-frame reset =====
        $display("\n===== Mid-frame reset =====");
        cpol_i = 0; cpha_i = 0; lsbfe_i = 0;
        apply_reset;
        test_reset_mid_frame;
        #20;
 
        $display("\n[%0t] Simulation complete", $time);
        $finish;
    end
 
    // -----------------------------------------------------------------------
    // Monitor
    // -----------------------------------------------------------------------
    initial begin
        $monitor("[%0t] ss=%b send=%b mosi=%b miso=%b rcv=%b data_miso=%h | cnt=%0d cnt1=%0d",
                 $time, ss_i, send_data_i, mosi_o, miso_i,
                 receive_data_i, data_miso_o,
                 dut.count, dut.count1);
    end
 
endmodule

sim/spi_top.sim/sim_1/behav/xsim/shift_reg_tb.vcd
$date
   Sat Jun 13 21:19:37 2026
$end

$version
  2025.1.0
  $dumpfile ("shift_reg_tb.vcd") 
$end

$timescale
  1ps
$end

$scope module shift_reg_tb $end
$var reg 1 ! PCLK $end
$var reg 1 " PRESET_n $end
$var reg 1 # ss_i $end
$var reg 1 $ send_data_i $end
$var reg 1 % lsbfe_i $end
$var reg 1 & cpha_i $end
$var reg 1 ' cpol_i $end
$var reg 1 ( miso_receive_sclk_i $end
$var reg 1 ) miso_receive_sclk0_i $end
$var reg 1 * mosi_send_sclk_i $end
$var reg 1 + mosi_send_sclk0_i $end
$var reg 8 , data_mosi_i [7:0] $end
$var reg 1 - miso_i $end
$var reg 1 . receive_data_i $end
$var wire 1 / mosi_o $end
$var wire 8 0 data_miso_o [7:0] $end
$var reg 8 1 captured_miso [7:0] $end
$scope module dut $end
$var wire 1 2 PCLK $end
$var wire 1 3 PRESET_n $end
$var wire 1 4 ss_i $end
$var wire 1 5 send_data_i $end
$var wire 1 6 lsbfe_i $end
$var wire 1 7 cpha_i $end
$var wire 1 8 cpol_i $end
$var wire 1 9 miso_receive_sclk_i $end
$var wire 1 : miso_receive_sclk0_i $end
$var wire 1 ; mosi_send_sclk_i $end
$var wire 1 < mosi_send_sclk0_i $end
$var wire 8 = data_mosi_i [7:0] $end
$var wire 1 > miso_i $end
$var wire 1 ? receive_data_i $end
$var reg 1 @ mosi_o $end
$var wire 8 0 data_miso_o [7:0] $end
$var reg 8 A shift_register [7:0] $end
$var reg 8 B temp_reg [7:0] $end
$var reg 8 C temp [7:0] $end
$var reg 3 D count [2:0] $end
$var reg 3 E count1 [2:0] $end
$var reg 3 F count2 [2:0] $end
$var reg 3 G count3 [2:0] $end
$var wire 1 H clk_wire $end
$var wire 1 I miso_sample_en $end
$upscope $end
$scope function clk_sel $end
$var reg 1 J clk_sel $end
$var reg 1 K dummy $end
$upscope $end
$scope task apply_reset $end
$upscope $end
$scope task load_mosi $end
$var reg 8 L data [7:0] $end
$upscope $end
$scope task start_spi $end
$upscope $end
$scope task stop_spi $end
$upscope $end
$scope task send_mosi_bit $end
$upscope $end
$scope task receive_miso_bit $end
$var reg 1 M bit_val $end
$upscope $end
$scope task read_received_data $end
$upscope $end
$scope task send_8_bits $end
$var reg 8 N data [7:0] $end
$var reg 8 O captured_bits [7:0] $end
$var integer 32 P i [31:0] $end
$upscope $end
$scope task receive_8_bits $end
$var reg 8 Q rx_pattern [7:0] $end
$var reg 8 R expected [7:0] $end
$var integer 32 S i [31:0] $end
$upscope $end
$scope task test_reset_mid_frame $end
$upscope $end
$upscope $end
$enddefinitions $end

#0
$dumpvars
0!
0"
1#
0$
0%
0&
0'
0(
0)
0*
0+
b0 ,
0-
0.
0/
b0 0
bx 1
02
03
14
05
06
07
08
09
0:
0;
0<
b0 =
0>
0?
0@
b0 A
b0 B
b0 C
b0 D
b111 E
b0 F
b111 G
0H
0I
xJ
xK
bx L
xM
bx N
bx O
bx P
bx Q
bx R
bx S
$end

#5000
1!
12

#10000
0!
02

#15000
1!
12

#20000
0!
02

#25000
1!
12

#30000
0!
1"
02
13
b10100101 L
b10100101 N

#35000
1!
12

#40000
0!
1$
b10100101 ,
02
15
b10100101 =

#45000
1!
12
b10100101 A

#50000
0!
0$
02
05

#55000
1!
12

#60000
0!
0#
02
04
b0 O
b0 P

#65000
1!
12

#70000
0!
1+
02
1<
0J
0K

#75000
1!
1/
12
1@
b110 E

#80000
0!
0+
02
0<
b1 O
b1 P

#85000
1!
12

#90000
0!
1+
02
1<

#95000
1!
0/
12
0@
b101 E

#100000
0!
0+
02
0<
b10 P

#105000
1!
12

#110000
0!
1+
02
1<

#115000
1!
1/
12
1@
b100 E

#120000
0!
0+
02
0<
b101 O
b11 P

#125000
1!
12

#130000
0!
1+
02
1<

#135000
1!
0/
12
0@
b11 E

#140000
0!
0+
02
0<
b100 P

#145000
1!
12

#150000
0!
1+
02
1<

#155000
1!
12
b10 E

#160000
0!
0+
02
0<
b101 P

#165000
1!
12

#170000
0!
1+
02
1<

#175000
1!
1/
12
1@
b1 E

#180000
0!
0+
02
0<
b100101 O
b110 P

#185000
1!
12

#190000
0!
1+
02
1<

#195000
1!
0/
12
0@
b0 E

#200000
0!
0+
02
0<
b111 P

#205000
1!
12

#210000
0!
1+
02
1<

#215000
1!
1/
12
1@
b111 E

#220000
0!
0+
02
0<
b10100101 O
b1000 P

#225000
1!
12

#230000
0!
1#
02
14

#235000
1!
0/
12
0@

#240000
0!
02

#245000
1!
12

#250000
0!
0"
1%
b0 ,
02
03
16
b0 =
b0 A

#255000
1!
12

#260000
0!
02

#265000
1!
12

#270000
0!
02

#275000
1!
12

#280000
0!
1"
02
13

#285000
1!
12

#290000
0!
1$
b10100101 ,
02
15
b10100101 =

#295000
1!
12
b10100101 A

#300000
0!
0$
02
05

#305000
1!
12

#310000
0!
0#
02
04
b0 O
b0 P

#315000
1!
12

#320000
0!
1+
02
1<

#325000
1!
1/
12
1@
b1 D

#330000
0!
0+
02
0<
b1 O
b1 P

#335000
1!
12

#340000
0!
1+
02
1<

#345000
1!
0/
12
0@
b10 D

#350000
0!
0+
02
0<
b10 P

#355000
1!
12

#360000
0!
1+
02
1<

#365000
1!
1/
12
1@
b11 D

#370000
0!
0+
02
0<
b101 O
b11 P

#375000
1!
12

#380000
0!
1+
02
1<

#385000
1!
0/
12
0@
b100 D

#390000
0!
0+
02
0<
b100 P

#395000
1!
12

#400000
0!
1+
02
1<

#405000
1!
12
b101 D

#410000
0!
0+
02
0<
b101 P

#415000
1!
12

#420000
0!
1+
02
1<

#425000
1!
1/
12
1@
b110 D

#430000
0!
0+
02
0<
b100101 O
b110 P

#435000
1!
12

#440000
0!
1+
02
1<

#445000
1!
0/
12
0@
b111 D

#450000
0!
0+
02
0<
b111 P

#455000
1!
12

#460000
0!
1+
02
1<

#465000
1!
1/
12
1@
b0 D

#470000
0!
0+
02
0<
b10100101 O
b1000 P

#475000
1!
12

#480000
0!
1#
02
14

#485000
1!
0/
12
0@

#490000
0!
02

#495000
1!
12

#500000
0!
0"
0%
b0 ,
02
03
06
b0 =
b0 A

#505000
1!
12

#510000
0!
02

#515000
1!
12

#520000
0!
02

#525000
1!
12

#530000
0!
1"
02
13
b11001100 Q
b11001100 R

#535000
1!
12

#540000
0!
0#
02
04
1M
b111 S

#545000
1!
12

#550000
0!
1(
1-
02
19
1>
1I

#555000
1!
12
b10000000 C
b110 G

#560000
0!
0(
02
09
0I
b110 S

#565000
1!
12

#570000
0!
1(
02
19
1I

#575000
1!
12
b11000000 C
b101 G

#580000
0!
0(
02
09
0I
0M
b101 S

#585000
1!
12

#590000
0!
1(
0-
02
19
0>
1I

#595000
1!
12
b100 G

#600000
0!
0(
02
09
0I
b100 S

#605000
1!
12

#610000
0!
1(
02
19
1I

#615000
1!
12
b11 G

#620000
0!
0(
02
09
0I
1M
b11 S

#625000
1!
12

#630000
0!
1(
1-
02
19
1>
1I

#635000
1!
12
b11001000 C
b10 G

#640000
0!
0(
02
09
0I
b10 S

#645000
1!
12

#650000
0!
1(
02
19
1I

#655000
1!
12
b11001100 C
b1 G

#660000
0!
0(
02
09
0I
0M
b1 S

#665000
1!
12

#670000
0!
1(
0-
02
19
0>
1I

#675000
1!
12
b0 G

#680000
0!
0(
02
09
0I
b0 S

#685000
1!
12

#690000
0!
1(
02
19
1I

#695000
1!
12
b111 G

#700000
0!
0(
02
09
0I
b11111111111111111111111111111111 S

#705000
1!
12

#710000
0!
1.
02
1?

#715000
1!
b11001100 0
12
b11001100 B

#720000
0!
0.
b0 0
b11001100 1
02
0?

#725000
1!
12

#730000
0!
1#
02
14

#735000
1!
12

#740000
0!
02

#745000
1!
12

#750000
0!
0"
1%
02
03
16
b0 B
b0 C

#755000
1!
12

#760000
0!
02

#765000
1!
12

#770000
0!
02

#775000
1!
12

#780000
0!
1"
02
13
b110011 R

#785000
1!
12

#790000
0!
0#
02
04
1M
b111 S

#795000
1!
12

#800000
0!
1(
1-
02
19
1>
1I

#805000
1!
12
b1 C
b1 F

#810000
0!
0(
02
09
0I
b110 S

#815000
1!
12

#820000
0!
1(
02
19
1I

#825000
1!
12
b11 C
b10 F

#830000
0!
0(
02
09
0I
0M
b101 S

#835000
1!
12

#840000
0!
1(
0-
02
19
0>
1I

#845000
1!
12
b11 F

#850000
0!
0(
02
09
0I
b100 S

#855000
1!
12

#860000
0!
1(
02
19
1I

#865000
1!
12
b100 F

#870000
0!
0(
02
09
0I
1M
b11 S

#875000
1!
12

#880000
0!
1(
1-
02
19
1>
1I

#885000
1!
12
b10011 C
b101 F

#890000
0!
0(
02
09
0I
b10 S

#895000
1!
12

#900000
0!
1(
02
19
1I

#905000
1!
12
b110011 C
b110 F

#910000
0!
0(
02
09
0I
0M
b1 S

#915000
1!
12

#920000
0!
1(
0-
02
19
0>
1I

#925000
1!
12
b111 F

#930000
0!
0(
02
09
0I
b0 S

#935000
1!
12

#940000
0!
1(
02
19
1I

#945000
1!
12
b0 F

#950000
0!
0(
02
09
0I
b11111111111111111111111111111111 S

#955000
1!
12

#960000
0!
1.
02
1?

#965000
1!
b110011 0
12
b110011 B

#970000
0!
0.
b0 0
b110011 1
02
0?

#975000
1!
12

#980000
0!
1#
02
14

#985000
1!
12

#990000
0!
02

#995000
1!
12

#1000000
0!
0"
0%
1&
02
03
06
17
b0 B
b0 C
1H

#1005000
1!
12

#1010000
0!
02

#1015000
1!
12

#1020000
0!
02

#1025000
1!
12

#1030000
0!
1"
02
13
b1011010 L
b1011010 N

#1035000
1!
12

#1040000
0!
1$
b1011010 ,
02
15
b1011010 =

#1045000
1!
12
b1011010 A

#1050000
0!
0$
02
05

#1055000
1!
12

#1060000
0!
0#
02
04
b0 O
b0 P

#1065000
1!
12

#1070000
0!
1*
02
1;
1J

#1075000
1!
12
b110 E

#1080000
0!
0*
02
0;
b1 P

#1085000
1!
12

#1090000
0!
1*
02
1;

#1095000
1!
1/
12
1@
b101 E

#1100000
0!
0*
02
0;
b10 O
b10 P

#1105000
1!
12

#1110000
0!
1*
02
1;

#1115000
1!
0/
12
0@
b100 E

#1120000
0!
0*
02
0;
b11 P

#1125000
1!
12

#1130000
0!
1*
02
1;

#1135000
1!
1/
12
1@
b11 E

#1140000
0!
0*
02
0;
b1010 O
b100 P

#1145000
1!
12

#1150000
0!
1*
02
1;

#1155000
1!
12
b10 E

#1160000
0!
0*
02
0;
b11010 O
b101 P

#1165000
1!
12

#1170000
0!
1*
02
1;

#1175000
1!
0/
12
0@
b1 E

#1180000
0!
0*
02
0;
b110 P

#1185000
1!
12

#1190000
0!
1*
02
1;

#1195000
1!
1/
12
1@
b0 E

#1200000
0!
0*
02
0;
b1011010 O
b111 P

#1205000
1!
12

#1210000
0!
1*
02
1;

#1215000
1!
0/
12
0@
b111 E

#1220000
0!
0*
02
0;
b1000 P

#1225000
1!
12

#1230000
0!
1#
02
14

#1235000
1!
12

#1240000
0!
02

#1245000
1!
12

#1250000
0!
0"
0&
1'
b0 ,
02
03
07
18
b0 =
b0 A

#1255000
1!
12

#1260000
0!
02

#1265000
1!
12

#1270000
0!
02

#1275000
1!
12

#1280000
0!
1"
02
13

#1285000
1!
12

#1290000
0!
1$
b1011010 ,
02
15
b1011010 =

#1295000
1!
12
b1011010 A

#1300000
0!
0$
02
05

#1305000
1!
12

#1310000
0!
0#
02
04
b0 O
b0 P

#1315000
1!
12

#1320000
0!
1*
02
1;

#1325000
1!
12
b110 E

#1330000
0!
0*
02
0;
b1 P

#1335000
1!
12

#1340000
0!
1*
02
1;

#1345000
1!
1/
12
1@
b101 E

#1350000
0!
0*
02
0;
b10 O
b10 P

#1355000
1!
12

#1360000
0!
1*
02
1;

#1365000
1!
0/
12
0@
b100 E

#1370000
0!
0*
02
0;
b11 P

#1375000
1!
12

#1380000
0!
1*
02
1;

#1385000
1!
1/
12
1@
b11 E

#1390000
0!
0*
02
0;
b1010 O
b100 P

#1395000
1!
12

#1400000
0!
1*
02
1;

#1405000
1!
12
b10 E

#1410000
0!
0*
02
0;
b11010 O
b101 P

#1415000
1!
12

#1420000
0!
1*
02
1;

#1425000
1!
0/
12
0@
b1 E

#1430000
0!
0*
02
0;
b110 P

#1435000
1!
12

#1440000
0!
1*
02
1;

#1445000
1!
1/
12
1@
b0 E

#1450000
0!
0*
02
0;
b1011010 O
b111 P

#1455000
1!
12

#1460000
0!
1*
02
1;

#1465000
1!
0/
12
0@
b111 E

#1470000
0!
0*
02
0;
b1000 P

#1475000
1!
12

#1480000
0!
1#
02
14

#1485000
1!
12

#1490000
0!
02

#1495000
1!
12

#1500000
0!
0"
1&
b0 ,
02
03
17
b0 =
b0 A
0H

#1505000
1!
12

#1510000
0!
02

#1515000
1!
12

#1520000
0!
02

#1525000
1!
12

#1530000
0!
1"
02
13

#1535000
1!
12

#1540000
0!
1$
b1011010 ,
02
15
b1011010 =

#1545000
1!
12
b1011010 A

#1550000
0!
0$
02
05

#1555000
1!
12

#1560000
0!
0#
02
04
b0 O
b0 P

#1565000
1!
12

#1570000
0!
1+
02
1<
0J

#1575000
1!
12
b110 E

#1580000
0!
0+
02
0<
b1 P

#1585000
1!
12

#1590000
0!
1+
02
1<

#1595000
1!
1/
12
1@
b101 E

#1600000
0!
0+
02
0<
b10 O
b10 P

#1605000
1!
12

#1610000
0!
1+
02
1<

#1615000
1!
0/
12
0@
b100 E

#1620000
0!
0+
02
0<
b11 P

#1625000
1!
12

#1630000
0!
1+
02
1<

#1635000
1!
1/
12
1@
b11 E

#1640000
0!
0+
02
0<
b1010 O
b100 P

#1645000
1!
12

#1650000
0!
1+
02
1<

#1655000
1!
12
b10 E

#1660000
0!
0+
02
0<
b11010 O
b101 P

#1665000
1!
12

#1670000
0!
1+
02
1<

#1675000
1!
0/
12
0@
b1 E

#1680000
0!
0+
02
0<
b110 P

#1685000
1!
12

#1690000
0!
1+
02
1<

#1695000
1!
1/
12
1@
b0 E

#1700000
0!
0+
02
0<
b1011010 O
b111 P

#1705000
1!
12

#1710000
0!
1+
02
1<

#1715000
1!
0/
12
0@
b111 E

