rtl/spi_baud_generator.v
`timescale 1ns / 1ps
//////////////////////////////////////////////////////////////////////////////////
// Company: 
// Engineer: 
// 
// Create Date: 16.01.2026 20:48:06
// Design Name: 
// Module Name: spi_baud_generator
// Project Name: 
// Target Devices: 
// Tool Versions: 
// Description: SPI Baud-Rate / Clock Generator
//            Generates sclk, miso-receive strobes, and
//            mosi-send strobes aligned to the SPI mode.
// 
// Dependencies: 
// 
// Revision:
// Revision 0.01 - File Created
// Additional Comments:
// 
//////////////////////////////////////////////////////////////////////////////////


module spi_baud_generator (
    // ---- System ----
    input        PCLK,
    input        PRESET_n,
 
    // ---- SPI configuration ----
    input  [1:0] spi_mode_i,   // 2'b00 / 2'b01 = master modes
    input        spiswai_i,    // SPI stop-in-wait
    input  [2:0] sppr_i,       // Baud-rate pre-scaler prescaler bits
    input  [2:0] spr_i,        // Baud-rate scaler bits
    input        cpol_i,       // Clock polarity
    input        cpha_i,       // Clock phase
    input        ss_i,         // Slave-select (active-low)
 
    // ---- Outputs ----
    output reg        sclk_o,
    output reg        miso_receive_sclk_o,
    output reg        miso_receive_sclk0_o,
    output reg        mosi_send_sclk_o,
    output reg        mosi_send_sclk0_o,
    output     [11:0] BaudRateDivisor_o
);
 
// ============================================================
// 1.  BAUD-RATE DIVISOR
//     BaudRateDivisor = (SPPR+1) * 2^(SPR+1)
//     Using left-shift for the power-of-2 multiply.
// ============================================================
assign BaudRateDivisor_o = (sppr_i + 1'b1) * (1'b1 << (spr_i + 1'b1));
 
// ============================================================
// 2.  PRE-SCLK  (idle level determined by CPOL)
// ============================================================
wire Pre_Sclk;
assign Pre_Sclk = cpol_i ? 1'b1 : 1'b0;
 
// ============================================================
// 3.  INTERNAL SIGNALS
// ============================================================
reg  [11:0] count;
 
// enable: master mode active, SS asserted (low), not in wait
wire enable;
assign enable = (  (spi_mode_i == 2'b10) || (spi_mode_i == 2'b01)  )
                && (~ss_i)
                && (~spiswai_i);
 
// Half-period compare values
//   hit  fires at  (BaudRateDivisor/2 - 1)  → toggle sclk, latch MISO
//   hit1 fires at  (BaudRateDivisor/2 - 2)  → advance MOSI (one cycle early)
wire hit;
wire hit1;
assign hit  = (count == ((BaudRateDivisor_o >> 1) - 1'b1));
assign hit1 = (count == ((BaudRateDivisor_o >> 1) - 2'b10));
 
// exor_in selects the active sclk edge for sampling / shifting
//   CPOL=0,CPHA=0 → exor_in=0  sample on rising  edge (sclk goes 0→1)
//   CPOL=0,CPHA=1 → exor_in=1  sample on falling edge (sclk goes 1→0)
//   CPOL=1,CPHA=0 → exor_in=1
//   CPOL=1,CPHA=1 → exor_in=0
wire exor_in;
assign exor_in = cpol_i ^ cpha_i;
 
// ============================================================
// 4.  COUNTER
//     Counts from 0 to (BaudRateDivisor/2 - 1) then wraps.
//     Resets to 0 whenever the block is disabled.
// ============================================================
always @(posedge PCLK or negedge PRESET_n) begin
    if (!PRESET_n)
        count <= 12'b0;
    else begin
        if (!enable)
            count <= 12'b0;
        else if (hit)
            count <= 12'b0;
        else
            count <= count + 1'b1;
    end
end
 
// ============================================================
// 5.  SCLK GENERATION
//     Toggles every (BaudRateDivisor/2) PCLK cycles.
//     Idles at Pre_Sclk when disabled.
// ============================================================
always @(posedge PCLK or negedge PRESET_n) begin
    if (!PRESET_n)
        sclk_o <= Pre_Sclk;
    else begin
        if (!enable)
            sclk_o <= Pre_Sclk;
        else if (hit)
            sclk_o <= ~sclk_o;
        // else hold
    end
end
 
// ============================================================
// 6.  MISO RECEIVE STROBES
//
//  exor_in = 1  →  sample on the rising edge of sclk
//                  strobe = miso_receive_sclk0_o
//                  fires when sclk_o is HIGH and hit occurs
//                  (next edge will be falling)
//
//  exor_in = 0  →  sample on the falling edge of sclk
//                  strobe = miso_receive_sclk_o
//                  fires when sclk_o is LOW  and hit occurs
//                  (next edge will be rising)
//
//  The unused strobe is always held at 0.
// ============================================================
always @(posedge PCLK or negedge PRESET_n) begin
    if (!PRESET_n) begin
        miso_receive_sclk_o  <= 1'b0;
        miso_receive_sclk0_o <= 1'b0;
    end
    else begin
        if (exor_in) begin
            // --- sample on sclk rising edge ---
            miso_receive_sclk_o  <= 1'b0;          // unused path → 0
            if (sclk_o && hit)
                miso_receive_sclk0_o <= 1'b1;      // pulse one PCLK wide
            else
                miso_receive_sclk0_o <= 1'b0;
        end
        else begin
            // --- sample on sclk falling edge ---
            miso_receive_sclk0_o <= 1'b0;          // unused path → 0
            if (!sclk_o && hit)
                miso_receive_sclk_o  <= 1'b1;      // pulse one PCLK wide
            else
                miso_receive_sclk_o  <= 1'b0;
        end
    end
end
 
// ============================================================
// 7.  MOSI SEND STROBES
//
//  MOSI data must be placed on the bus BEFORE the sampling edge,
//  so the strobe fires one count earlier (hit1 instead of hit).
//
//  exor_in = 1  →  shift out just before sclk rising edge
//                  strobe = mosi_send_sclk_o
//                  fires when sclk_o is HIGH and hit1 occurs
//
//  exor_in = 0  →  shift out just before sclk falling edge
//                  strobe = mosi_send_sclk0_o
//                  fires when sclk_o is LOW  and hit1 occurs
//
//  The unused strobe is always held at 0.
// ============================================================
always @(posedge PCLK or negedge PRESET_n) begin
    if (!PRESET_n) begin
        mosi_send_sclk_o  <= 1'b0;
        mosi_send_sclk0_o <= 1'b0;
    end
    else begin
        if (exor_in) begin
            // --- shift before sclk rising edge ---
            mosi_send_sclk0_o <= 1'b0;             // unused path → 0
            if (sclk_o && hit1)
                mosi_send_sclk_o  <= 1'b1;
            else
                mosi_send_sclk_o  <= 1'b0;
        end
        else begin
            // --- shift before sclk falling edge ---
            mosi_send_sclk_o  <= 1'b0;             // unused path → 0
            if (!sclk_o && hit1)
                mosi_send_sclk0_o <= 1'b1;
            else
                mosi_send_sclk0_o <= 1'b0;
        end
    end
end
 
endmodule

tb/spi_baud_generator_tb.v
`timescale 1ns / 1ps
//////////////////////////////////////////////////////////////////////////////////
// Company: 
// Engineer: 
// 
// Create Date: 16.01.2026 21:58:08
// Design Name: 
// Module Name: spi_baud_generator_tb
// Project Name: 
// Target Devices: 
// Tool Versions: 
// Description: 
// 
// Dependencies: 
// 
// Revision:
// Revision 0.01 - File Created
// Additional Comments:
// 
//////////////////////////////////////////////////////////////////////////////////


module spi_baud_generator_tb;
 
// ----------------------------------------------------------------
// DUT ports
// ----------------------------------------------------------------
reg        PCLK;
reg        PRESET_n;
reg  [1:0] spi_mode_i;
reg        spiswai_i;
reg  [2:0] sppr_i, spr_i;
reg        cpol_i, cpha_i;
reg        ss_i;
 
wire        sclk_o;
wire        miso_receive_sclk_o;
wire        miso_receive_sclk0_o;
wire        mosi_send_sclk_o;
wire        mosi_send_sclk0_o;
wire [11:0] BaudRateDivisor_o;
 
// ----------------------------------------------------------------
// Encoding constants - MUST match apb_slave localparams
// ----------------------------------------------------------------
localparam SPI_RUN  = 2'b10;
localparam SPI_WAIT = 2'b01;
localparam SPI_STOP = 2'b00;
 
// ----------------------------------------------------------------
// DUT instantiation
// ----------------------------------------------------------------
spi_baud_generator dut (
    .PCLK                 (PCLK),
    .PRESET_n             (PRESET_n),
    .spi_mode_i           (spi_mode_i),
    .spiswai_i            (spiswai_i),
    .sppr_i               (sppr_i),
    .spr_i                (spr_i),
    .cpol_i               (cpol_i),
    .cpha_i               (cpha_i),
    .ss_i                 (ss_i),
    .sclk_o               (sclk_o),
    .miso_receive_sclk_o  (miso_receive_sclk_o),
    .miso_receive_sclk0_o (miso_receive_sclk0_o),
    .mosi_send_sclk_o     (mosi_send_sclk_o),
    .mosi_send_sclk0_o    (mosi_send_sclk0_o),
    .BaudRateDivisor_o    (BaudRateDivisor_o)
);
 
// ----------------------------------------------------------------
// Clock - 10 ns period (100 MHz)
// ----------------------------------------------------------------
initial PCLK = 1'b0;
always #5 PCLK = ~PCLK;
 
// ----------------------------------------------------------------
// TASKS
// ----------------------------------------------------------------
 
// Active-low reset
task reset_dut;
begin
    PRESET_n = 1'b0;
    repeat(4) @(posedge PCLK);
    PRESET_n = 1'b1;
    @(posedge PCLK);
end
endtask
 
// Safe idle state
task initialize;
begin
    spi_mode_i = SPI_STOP;  // 2'b00 - disabled
    spiswai_i  = 1'b0;
    sppr_i     = 3'b000;
    spr_i      = 3'b000;
    cpol_i     = 1'b0;
    cpha_i     = 1'b0;
    ss_i       = 1'b1;      // deasserted (active-low)
end
endtask
 
// Set clock polarity / phase
task clock_mode;
    input cpol, cpha;
begin
    cpol_i = cpol;
    cpha_i = cpha;
end
endtask
 
// Set baud-rate divisor inputs
task set_divisor;
    input [2:0] sppr, spr;
begin
    sppr_i = sppr;
    spr_i  = spr;
end
endtask
 
// Set SPI enable controls
// mode must use SPI_RUN/SPI_WAIT/SPI_STOP constants above
task set_enable;
    input        ss, swai;
    input [1:0]  mode;
begin
    ss_i       = ss;
    spiswai_i  = swai;
    spi_mode_i = mode;
end
endtask
 
// Flush: deassert ss + stop mode for a full BRD period to cleanly reset
task flush_state;
begin
    set_enable(1'b1, 1'b0, SPI_STOP);
    repeat(BaudRateDivisor_o) @(posedge PCLK);
end
endtask
 
// Wait N full sclk half-periods (each = BaudRateDivisor/2 PCLKs)
task wait_half_periods;
    input integer n;
    integer i;
begin
    for (i = 0; i < n; i = i + 1)
        repeat(BaudRateDivisor_o >> 1) @(posedge PCLK);
end
endtask
 
// ----------------------------------------------------------------
// DISPLAY HELPER
// ----------------------------------------------------------------
task print_state;
begin
    $display("T=%0t | sclk=%b | CPOL=%b CPHA=%b | BRD=%0d | cnt=%0d | miso_sclk=%b miso_sclk0=%b | mosi_sclk=%b mosi_sclk0=%b",
             $time, sclk_o, cpol_i, cpha_i, BaudRateDivisor_o, dut.count,
             miso_receive_sclk_o, miso_receive_sclk0_o,
             mosi_send_sclk_o,    mosi_send_sclk0_o);
end
endtask
 
// ----------------------------------------------------------------
// STIMULUS
// ----------------------------------------------------------------
initial begin
    $dumpfile("spi_baud_generator_tb.vcd");
    $dumpvars(0, spi_baud_generator_tb);
 
    initialize();
    reset_dut();
 
    // ============================================================
    // TEST 1 : CPOL=0, CPHA=0  (exor_in=0)
    //          SPPR=1, SPR=0 → BRD=4, half-period=2 PCLKs
    //          FIX: mode = SPI_RUN (2'b10) not 2'b00
    // ============================================================
    $display("\n===== TEST 1 : CPOL=0 CPHA=0, BRD=4 =====");
    clock_mode(0, 0);
    set_divisor(3'b001, 3'b000);
    flush_state();                          // clean start
    set_enable(1'b0, 1'b0, SPI_RUN);       // ss=0, mode=SPI_RUN
    wait_half_periods(8);
    flush_state();
 
    // ============================================================
    // TEST 2 : CPOL=0, CPHA=1  (exor_in=1)
    //          FIX: mode = SPI_RUN
    // ============================================================
    $display("\n===== TEST 2 : CPOL=0 CPHA=1, BRD=4 =====");
    clock_mode(0, 1);
    set_divisor(3'b001, 3'b000);
    flush_state();
    set_enable(1'b0, 1'b0, SPI_RUN);
    wait_half_periods(8);
    flush_state();
 
    // ============================================================
    // TEST 3 : CPOL=1, CPHA=0  (exor_in=1)
    //          sclk idles HIGH when disabled
    // ============================================================
    $display("\n===== TEST 3 : CPOL=1 CPHA=0, BRD=4 =====");
    clock_mode(1, 0);
    set_divisor(3'b001, 3'b000);
    flush_state();
    set_enable(1'b0, 1'b0, SPI_RUN);
    wait_half_periods(8);
    flush_state();
 
    // ============================================================
    // TEST 4 : CPOL=1, CPHA=1  (exor_in=0)
    // ============================================================
    $display("\n===== TEST 4 : CPOL=1 CPHA=1, BRD=4 =====");
    clock_mode(1, 1);
    set_divisor(3'b001, 3'b000);
    flush_state();
    set_enable(1'b0, 1'b0, SPI_RUN);
    wait_half_periods(8);
    flush_state();
 
    // ============================================================
    // TEST 5 : Larger divisor - SPPR=2, SPR=2
    //          BRD = (2+1)*2^(2+1) = 24, half-period=12 PCLKs
    // ============================================================
    $display("\n===== TEST 5 : CPOL=0 CPHA=0, BRD=24 =====");
    clock_mode(0, 0);
    set_divisor(3'b010, 3'b010);
    flush_state();
    set_enable(1'b0, 1'b0, SPI_RUN);
    wait_half_periods(6);
    flush_state();
 
    // ============================================================
    // TEST 6 : SS de-assert mid-transfer then re-assert
    //          FIX: wait full BRD after deassert before re-assert
    // ============================================================
    $display("\n===== TEST 6 : SS toggle mid-transfer =====");
    clock_mode(0, 0);
    set_divisor(3'b001, 3'b000);
    flush_state();
    set_enable(1'b0, 1'b0, SPI_RUN);
    wait_half_periods(4);               // 2 sclk cycles active
    // Deassert SS - sclk must return to idle (0 for CPOL=0)
    set_enable(1'b1, 1'b0, SPI_RUN);
    repeat(BaudRateDivisor_o) @(posedge PCLK);   // full flush
    $display("T=%0t | After SS deassert: sclk_o=%b (expect 0)", $time, sclk_o);
    // Re-assert SS - transfer resumes cleanly from cycle start
    set_enable(1'b0, 1'b0, SPI_RUN);
    wait_half_periods(4);
    flush_state();
 
    // ============================================================
    // TEST 7 : SPISWAI disable - sclk must freeze at idle
    //          FIX: wait full BRD before re-enabling
    // ============================================================
    $display("\n===== TEST 7 : SPISWAI disable =====");
    clock_mode(0, 0);
    set_divisor(3'b001, 3'b000);
    flush_state();
    set_enable(1'b0, 1'b0, SPI_RUN);
    wait_half_periods(3);
    // Assert SPISWAI - baud gen must stop
    set_enable(1'b0, 1'b1, SPI_RUN);
    repeat(BaudRateDivisor_o) @(posedge PCLK);   // full flush
    $display("T=%0t | After SPISWAI: sclk_o=%b (expect 0)", $time, sclk_o);
    flush_state();
    set_enable(1'b0, 1'b0, SPI_RUN);
    wait_half_periods(4);
    flush_state();
 
    // ============================================================
    // TEST 8 : SPI_STOP mode - sclk must NOT toggle
    //          FIX: drive SPI_STOP (2'b00) not SPI_RUN (2'b10)
    //          Previous TB drove 2'b10 calling it "slave mode"
    //          but 2'b10 = SPI_RUN = enables baud gen!
    // ============================================================
    $display("\n===== TEST 8 : SPI_STOP mode (2b00) - no toggle =====");
    clock_mode(0, 0);
    set_divisor(3'b001, 3'b000);
    flush_state();
    set_enable(1'b0, 1'b0, SPI_STOP);   // SPI_STOP = 2'b00
    repeat(20) @(posedge PCLK);
    $display("T=%0t | SPI_STOP: sclk_o=%b (expect 0, no toggle)", $time, sclk_o);
    // Also verify SPI_WAIT (2'b01) - should enable baud gen
    $display("T=%0t | Switching to SPI_WAIT (2b01)...", $time);
    set_enable(1'b0, 1'b0, SPI_WAIT);
    wait_half_periods(4);
    $display("T=%0t | SPI_WAIT: sclk_o=%b (expect toggling)", $time, sclk_o);
    flush_state();
 
    // ============================================================
    // TEST 9 : Reset during active transfer
    // ============================================================
    $display("\n===== TEST 9 : Reset during active transfer =====");
    clock_mode(0, 1);
    set_divisor(3'b001, 3'b000);
    flush_state();
    set_enable(1'b0, 1'b0, SPI_STOP);
    wait_half_periods(3);
    $display("T=%0t | Asserting reset mid-transfer", $time);
    PRESET_n = 1'b0;
    repeat(2) @(posedge PCLK);
    $display("T=%0t | During reset: sclk_o=%b count=%0d", $time, sclk_o, dut.count);
    PRESET_n = 1'b1;
    repeat(2) @(posedge PCLK);
    $display("T=%0t | After reset: sclk_o=%b count=%0d (expect 0)", $time, sclk_o, dut.count);
    flush_state();
 
    $display("\n===== ALL TESTS COMPLETE =====");
    #20;
    $finish;
end
 
// ----------------------------------------------------------------
// MONITORS
// ----------------------------------------------------------------
always @(posedge sclk_o or negedge sclk_o)
    print_state();
 
always @(posedge miso_receive_sclk_o or posedge miso_receive_sclk0_o or
         posedge mosi_send_sclk_o    or posedge mosi_send_sclk0_o) begin
    $display("T=%0t | STROBE >> miso_sclk=%b miso_sclk0=%b mosi_sclk=%b mosi_sclk0=%b",
             $time,
             miso_receive_sclk_o, miso_receive_sclk0_o,
             mosi_send_sclk_o,    mosi_send_sclk0_o);
end
 
endmodule

sim/spi_top.sim/sim_1/behav/xsim/spi_baud_generator_tb.vcd
$date
   Sun Jun 14 09:43:27 2026
$end

$version
  2025.1.0
  $dumpfile ("spi_baud_generator_tb.vcd") 
$end

$timescale
  1ps
$end

$scope module spi_baud_generator_tb $end
$var reg 1 ! PCLK $end
$var reg 1 " PRESET_n $end
$var reg 2 # spi_mode_i [1:0] $end
$var reg 1 $ spiswai_i $end
$var reg 3 % sppr_i [2:0] $end
$var reg 3 & spr_i [2:0] $end
$var reg 1 ' cpol_i $end
$var reg 1 ( cpha_i $end
$var reg 1 ) ss_i $end
$var wire 1 * sclk_o $end
$var wire 1 + miso_receive_sclk_o $end
$var wire 1 , miso_receive_sclk0_o $end
$var wire 1 - mosi_send_sclk_o $end
$var wire 1 . mosi_send_sclk0_o $end
$var wire 12 / BaudRateDivisor_o [11:0] $end
$scope module dut $end
$var wire 1 0 PCLK $end
$var wire 1 1 PRESET_n $end
$var wire 2 2 spi_mode_i [1:0] $end
$var wire 1 3 spiswai_i $end
$var wire 3 4 sppr_i [2:0] $end
$var wire 3 5 spr_i [2:0] $end
$var wire 1 6 cpol_i $end
$var wire 1 7 cpha_i $end
$var wire 1 8 ss_i $end
$var reg 1 9 sclk_o $end
$var reg 1 : miso_receive_sclk_o $end
$var reg 1 ; miso_receive_sclk0_o $end
$var reg 1 < mosi_send_sclk_o $end
$var reg 1 = mosi_send_sclk0_o $end
$var wire 12 / BaudRateDivisor_o [11:0] $end
$var wire 1 > Pre_Sclk $end
$var reg 12 ? count [11:0] $end
$var wire 1 @ enable $end
$var wire 1 A hit $end
$var wire 1 B hit1 $end
$var wire 1 C exor_in $end
$upscope $end
$scope task reset_dut $end
$upscope $end
$scope task initialize $end
$upscope $end
$scope task clock_mode $end
$var reg 1 D cpol $end
$var reg 1 E cpha $end
$upscope $end
$scope task set_divisor $end
$var reg 3 F sppr [2:0] $end
$var reg 3 G spr [2:0] $end
$upscope $end
$scope task set_enable $end
$var reg 1 H ss $end
$var reg 1 I swai $end
$var reg 2 J mode [1:0] $end
$upscope $end
$scope task flush_state $end
$upscope $end
$scope task wait_half_periods $end
$var integer 32 K n [31:0] $end
$var integer 32 L i [31:0] $end
$upscope $end
$scope task print_state $end
$upscope $end
$upscope $end
$enddefinitions $end

#0
$dumpvars
0!
0"
b0 #
0$
b0 %
b0 &
0'
0(
1)
0*
0+
0,
0-
0.
b10 /
00
01
b0 2
03
b0 4
b0 5
06
07
18
09
0:
0;
0<
0=
0>
b0 ?
0@
1A
0B
0C
xD
xE
bx F
bx G
xH
xI
bx J
bx K
bx L
$end

#5000
1!
10

#10000
0!
00

#15000
1!
10

#20000
0!
00

#25000
1!
10

#30000
0!
00

#35000
1!
1"
1+
10
11
1:

#40000
0!
00

#45000
1!
b1 %
b100 /
10
b1 4
0A
1B
0D
0E
b1 F
b0 G
1H
0I
b0 J

#50000
0!
00

#55000
1!
0+
1.
10
0:
1=

#60000
0!
00

#65000
1!
b10 #
0)
10
b10 2
08
1@
0H
b10 J
b1000 K
b0 L

#70000
0!
00

#75000
1!
10
b1 ?
1A
0B

#80000
0!
00

#85000
1!
1*
1+
0.
10
19
1:
0=
b0 ?
0A
1B
b1 L

#90000
0!
00

#95000
1!
0+
10
0:
b1 ?
1A
0B

#100000
0!
00

#105000
1!
0*
10
09
b0 ?
0A
1B
b10 L

#110000
0!
00

#115000
1!
1.
10
1=
b1 ?
1A
0B

#120000
0!
00

#125000
1!
1*
1+
0.
10
19
1:
0=
b0 ?
0A
1B
b11 L

#130000
0!
00

#135000
1!
0+
10
0:
b1 ?
1A
0B

#140000
0!
00

#145000
1!
0*
10
09
b0 ?
0A
1B
b100 L

#150000
0!
00

#155000
1!
1.
10
1=
b1 ?
1A
0B

#160000
0!
00

#165000
1!
1*
1+
0.
10
19
1:
0=
b0 ?
0A
1B
b101 L

#170000
0!
00

#175000
1!
0+
10
0:
b1 ?
1A
0B

#180000
0!
00

#185000
1!
0*
10
09
b0 ?
0A
1B
b110 L

#190000
0!
00

#195000
1!
1.
10
1=
b1 ?
1A
0B

#200000
0!
00

#205000
1!
1*
1+
0.
10
19
1:
0=
b0 ?
0A
1B
b111 L

#210000
0!
00

#215000
1!
0+
10
0:
b1 ?
1A
0B

#220000
0!
00

#225000
1!
b0 #
1)
0*
10
b0 2
18
09
b0 ?
0@
0A
1B
1H
b0 J
b1000 L

#230000
0!
00

#235000
1!
1.
10
1=

#240000
0!
00

#245000
1!
10

#250000
0!
00

#255000
1!
10

#260000
0!
00

#265000
1!
1(
10
17
1C
1E

#270000
0!
00

#275000
1!
0.
10
0=

#280000
0!
00

#285000
1!
10

#290000
0!
00

#295000
1!
10

#300000
0!
00

#305000
1!
b10 #
0)
10
b10 2
08
1@
0H
b10 J
b0 L

#310000
0!
00

#315000
1!
10
b1 ?
1A
0B

#320000
0!
00

#325000
1!
1*
10
19
b0 ?
0A
1B
b1 L

#330000
0!
00

#335000
1!
1-
10
1<
b1 ?
1A
0B

#340000
0!
00

#345000
1!
0*
1,
0-
10
09
1;
0<
b0 ?
0A
1B
b10 L

#350000
0!
00

#355000
1!
0,
10
0;
b1 ?
1A
0B

#360000
0!
00

#365000
1!
1*
10
19
b0 ?
0A
1B
b11 L

#370000
0!
00

#375000
1!
1-
10
1<
b1 ?
1A
0B

#380000
0!
00

#385000
1!
0*
1,
0-
10
09
1;
0<
b0 ?
0A
1B
b100 L

#390000
0!
00

#395000
1!
0,
10
0;
b1 ?
1A
0B

#400000
0!
00

#405000
1!
1*
10
19
b0 ?
0A
1B
b101 L

#410000
0!
00

#415000
1!
1-
10
1<
b1 ?
1A
0B

#420000
0!
00

#425000
1!
0*
1,
0-
10
09
1;
0<
b0 ?
0A
1B
b110 L

#430000
0!
00

#435000
1!
0,
10
0;
b1 ?
1A
0B

#440000
0!
00

#445000
1!
1*
10
19
b0 ?
0A
1B
b111 L

#450000
0!
00

#455000
1!
1-
10
1<
b1 ?
1A
0B

#460000
0!
00

#465000
1!
b0 #
1)
0*
1,
0-
10
b0 2
18
09
1;
0<
b0 ?
0@
0A
1B
1H
b0 J
b1000 L

#470000
0!
00

#475000
1!
0,
10
0;

#480000
0!
00

#485000
1!
10

#490000
0!
00

#495000
1!
10

#500000
0!
00

#505000
1!
1'
0(
10
16
07
1>
1D
0E

#510000
0!
00

#515000
1!
1*
10
19

#520000
0!
00

#525000
1!
1-
10
1<

#530000
0!
00

#535000
1!
10

#540000
0!
00

#545000
1!
b10 #
0)
10
b10 2
08
1@
0H
b10 J
b0 L

#550000
0!
00

#555000
1!
10
b1 ?
1A
0B

#560000
0!
00

#565000
1!
0*
1,
0-
10
09
1;
0<
b0 ?
0A
1B
b1 L

#570000
0!
00

#575000
1!
0,
10
0;
b1 ?
1A
0B

#580000
0!
00

#585000
1!
1*
10
19
b0 ?
0A
1B
b10 L

#590000
0!
00

#595000
1!
1-
10
1<
b1 ?
1A
0B

#600000
0!
00

#605000
1!
0*
1,
0-
10
09
1;
0<
b0 ?
0A
1B
b11 L

#610000
0!
00

#615000
1!
0,
10
0;
b1 ?
1A
0B

#620000
0!
00

#625000
1!
1*
10
19
b0 ?
0A
1B
b100 L

#630000
0!
00

#635000
1!
1-
10
1<
b1 ?
1A
0B

#640000
0!
00

#645000
1!
0*
1,
0-
10
09
1;
0<
b0 ?
0A
1B
b101 L

#650000
0!
00

#655000
1!
0,
10
0;
b1 ?
1A
0B

#660000
0!
00

#665000
1!
1*
10
19
b0 ?
0A
1B
b110 L

#670000
0!
00

#675000
1!
1-
10
1<
b1 ?
1A
0B

#680000
0!
00

#685000
1!
0*
1,
0-
10
09
1;
0<
b0 ?
0A
1B
b111 L

#690000
0!
00

#695000
1!
0,
10
0;
b1 ?
1A
0B

#700000
0!
00

#705000
1!
b0 #
1)
1*
10
b0 2
18
19
b0 ?
0@
0A
1B
1H
b0 J
b1000 L

#710000
0!
00

#715000
1!
1-
10
1<

#720000
0!
00

#725000
1!
10

#730000
0!
00

#735000
1!
10

#740000
0!
00

#745000
1!
1(
10
17
0C
1E

#750000
0!
00

#755000
1!
0-
10
0<

#760000
0!
00

#765000
1!
10

#770000
0!
00

#775000
1!
10

#780000
0!
00

#785000
1!
b10 #
0)
10
b10 2
08
1@
0H
b10 J
b0 L

#790000
0!
00

#795000
1!
10
b1 ?
1A
0B

#800000
0!
00

#805000
1!
0*
10
09
b0 ?
0A
1B
b1 L

#810000
0!
00

#815000
1!
1.
10
1=
b1 ?
1A
0B

#820000
0!
00

#825000
1!
1*
1+
0.
10
19
1:
0=
b0 ?
0A
1B
b10 L

#830000
0!
00

#835000
1!
0+
10
0:
b1 ?
1A
0B

#840000
0!
00

#845000
1!
0*
10
09
b0 ?
0A
1B
b11 L

#850000
0!
00

#855000
1!
1.
10
1=
b1 ?
1A
0B

#860000
0!
00

#865000
1!
1*
1+
0.
10
19
1:
0=
b0 ?
0A
1B
b100 L

#870000
0!
00

#875000
1!
0+
10
0:
b1 ?
1A
0B

#880000
0!
00

#885000
1!
0*
10
09
b0 ?
0A
1B
b101 L

#890000
0!
00

#895000
1!
1.
10
1=
b1 ?
1A
0B

#900000
0!
00

#905000
1!
1*
1+
0.
10
19
1:
0=
b0 ?
0A
1B
b110 L

#910000
0!
00

#915000
1!
0+
10
0:
b1 ?
1A
0B

#920000
0!
00

#925000
1!
0*
10
09
b0 ?
0A
1B
b111 L

#930000
0!
00

#935000
1!
1.
10
1=
b1 ?
1A
0B

#940000
0!
00

#945000
1!
b0 #
1)
1*
1+
0.
10
b0 2
18
19
1:
0=
b0 ?
0@
0A
1B
1H
b0 J
b1000 L

#950000
0!
00

#955000
1!
0+
10
0:

#960000
0!
00

#965000
1!
10

#970000
0!
00

#975000
1!
10

#980000
0!
00

#985000
1!
b10 %
b10 &
0'
0(
b11000 /
10
b10 4
b10 5
06
07
0>
0B
0D
0E
b10 F
b10 G

#990000
0!
00

#995000
1!
0*
10
09

#1000000
0!
00

#1005000
1!
10

#1010000
0!
00

#1015000
1!
10

#1020000
0!
00

#1025000
1!
b10 #
0)
10
b10 2
08
1@
0H
b10 J
b110 K
b0 L

#1030000
0!
00

#1035000
1!
10
b1 ?

#1040000
0!
00

#1045000
1!
10
b10 ?

#1050000
0!
00

#1055000
1!
10
b11 ?

#1060000
0!
00

#1065000
1!
10
b100 ?

#1070000
0!
00

#1075000
1!
10
b101 ?

#1080000
0!
00

#1085000
1!
10
b110 ?

#1090000
0!
00

#1095000
1!
10
b111 ?

#1100000
0!
00

#1105000
1!
10
b1000 ?

#1110000
0!
00

#1115000
1!
10
b1001 ?

#1120000
0!
00

#1125000
1!
10
b1010 ?
1B

#1130000
0!
00

#1135000
1!
1.
10
1=
b1011 ?
1A
0B

#1140000
0!
00

#1145000
1!
1*
1+
0.
10
19
1:
0=
b0 ?
0A
b1 L

#1150000
0!
00

#1155000
1!
0+
10
0:
b1 ?

#1160000
0!
00

#1165000
1!
10
b10 ?

#1170000
0!
00

#1175000
1!
10
b11 ?

#1180000
0!
00

#1185000
1!
10
b100 ?

#1190000
0!
00

#1195000
1!
10
b101 ?

#1200000
0!
00

#1205000
1!
10
b110 ?

#1210000
0!
00

#1215000
1!
10
b111 ?

#1220000
0!
00

#1225000
1!
10
b1000 ?

#1230000
0!
00

#1235000
1!
10
b1001 ?

#1240000
0!
00

#1245000
1!
10
b1010 ?
1B

#1250000
0!
00

#1255000
1!
10
b1011 ?
1A
0B

#1260000
0!
00

#1265000
1!
0*
10
09
b0 ?
0A
b10 L

#1270000
0!
00

#1275000
1!
10
b1 ?

#1280000
0!
00

#1285000
1!
10
b10 ?

#1290000
0!
00

#1295000
1!
10
b11 ?

#1300000
0!
00

#1305000
1!
10
b100 ?

#1310000
0!
00

#1315000
1!
10
b101 ?

#1320000
0!
00

#1325000
1!
10
b110 ?

#1330000
0!
00

#1335000
1!
10
b111 ?

#1340000
0!
00

#1345000
1!
10
b1000 ?

#1350000
0!
00

#1355000
1!
10
b1001 ?

#1360000
0!
00

#1365000
1!
10
b1010 ?
1B

#1370000
0!
00

#1375000
1!
1.
10
1=
b1011 ?
1A
0B

#1380000
0!
00

#1385000
1!
1*
1+
0.
10
19
1:
0=
b0 ?
0A
b11 L

#1390000
0!
00

#1395000
1!
0+
10
0:
b1 ?

#1400000
0!
00

#1405000
1!
10
b10 ?

#1410000
0!
00

#1415000
1!
10
b11 ?

#1420000
0!
00

#1425000
1!
10
b100 ?

#1430000
0!
00

#1435000
1!
10
b101 ?

#1440000
0!
00

#1445000
1!
10
b110 ?

#1450000
0!
00

#1455000
1!
10
b111 ?

#1460000
0!
00

#1465000
1!
10
b1000 ?

#1470000
0!
00

#1475000
1!
10
b1001 ?

#1480000
0!
00

#1485000
1!
10
b1010 ?
1B

#1490000
0!
00

#1495000
1!
10
b1011 ?
1A
0B

#1500000
0!
00

#1505000
1!
0*
10
09
b0 ?
0A
b100 L

#1510000
0!
00

#1515000
1!
10
b1 ?

#1520000
0!
00

#1525000
1!
10
b10 ?

#1530000
0!
00

#1535000
1!
10
b11 ?

#1540000
0!
00

#1545000
1!
10
b100 ?

#1550000
0!
00

#1555000
1!
10
b101 ?

#1560000
0!
00

#1565000
1!
10
b110 ?

#1570000
0!
00

#1575000
1!
10
b111 ?

#1580000
0!
00

#1585000
1!
10
b1000 ?

#1590000
0!
00

#1595000
1!
10
b1001 ?

#1600000
0!
00

#1605000
1!
10
b1010 ?
1B

#1610000
0!
00

#1615000
1!
1.
10
1=
b1011 ?
1A
0B

#1620000
0!
00

#1625000
1!
1*
1+
0.
10
19
1:
0=
b0 ?
0A
b101 L

#1630000
0!
00

#1635000
1!
0+
10
0:
b1 ?

#1640000
0!
00

#1645000
1!
10
b10 ?

#1650000
0!
00

#1655000
1!
10
b11 ?

#1660000
0!
00

#1665000
1!
10
b100 ?

#1670000
0!
00

#1675000
1!
10
b101 ?

#1680000
0!
00

#1685000
1!
10
b110 ?

#1690000
0!
00

#1695000
1!
10
b111 ?

#1700000
0!
00

#1705000
1!
10
b1000 ?

#1710000
0!
00

