rtl/spi_slave_select.v
`timescale 1ns / 1ps
//////////////////////////////////////////////////////////////////////////////////
// Company: 
// Engineer: 
// 
// Create Date: 20.01.2026 20:48:20
// Design Name: 
// Module Name: spi_slave_select
// Project Name: 
// Target Devices: 
// Tool Versions: 
// Description: 
// 
// Dependencies: 
// 
// Revision:
// Revision 0.01 - File Created
// Additional Comments:
// 
//////////////////////////////////////////////////////////////////////////////////


module spi_slave_select (
    input            PCLK,
    input            PRESET_n,
    input            mstr_i,
    input            spiswai_i,
    input  [1:0]     spi_mode_i,      
    input            send_data_i,
    input  [15:0]    BaudRateDivisor_i,
 
    output reg       receive_data_o,
    output reg       ss_o,
    output           tip_o
);
 
    reg  [15:0] count_s;
    reg         rcv_s;
 
    wire [15:0] target_s;
    wire        hit;          // count_s <= target_s - 1  (frame running)
    wire        hit1;         // count_s == target_s - 1  (last frame cycle)
    wire        spi_run;
    wire        spi_wait;
    wire        mode_ok;
    wire        enable;       

    assign target_s = BaudRateDivisor_i * 8;
 
    assign spi_run  = (spi_mode_i == 2'b10);          
    assign spi_wait = (spi_mode_i == 2'b01);
    assign mode_ok  = spi_run | spi_wait;
 
    assign enable   = (~spiswai_i) & mode_ok & mstr_i; 
 
    // hit  : frame is actively counting  (count_s <= target_s - 1)
    // hit1 : very last count value        (count_s == target_s - 1)
    assign hit  = (count_s <= (target_s - 1'b1));
    assign hit1 = (count_s == (target_s - 1'b1));
 
    // tip_o: complement of ss_o  
    assign tip_o = ~ss_o;
 
    always @(posedge PCLK or negedge PRESET_n) begin
        if (!PRESET_n)
            count_s <= 16'hFFFF;
        else if (!enable)
            count_s <= 16'hFFFF;
        else begin                          // enable = 1
            if (send_data_i)
                count_s <= 16'd0;           // load 16'b0  
            else if (hit)
                count_s <= count_s + 1'b1;  // increment  
            else
                count_s <= 16'hFFFF;        // frame done → idle
        end
    end
 
    always @(posedge PCLK or negedge PRESET_n) begin
        if (!PRESET_n)
            rcv_s <= 1'b0;
        else if (!enable)
            rcv_s <= 1'b0;
        else begin                          // enable = 1
            if (send_data_i)
                rcv_s <= 1'b0;
            else if (!hit)
                rcv_s <= 1'b0;
            else
                rcv_s <= hit1;              // 1 only on last count 
        end
    end
 
    always @(posedge PCLK or negedge PRESET_n) begin
        if (!PRESET_n)
            receive_data_o <= 1'b0;
        else
            receive_data_o <= rcv_s;
    end
 
    always @(posedge PCLK or negedge PRESET_n) begin
        if (!PRESET_n)
            ss_o <= 1'b1;
        else if (!enable)
            ss_o <= 1'b1;
        else begin                          // enable = 1
            if (send_data_i)
                ss_o <= 1'b0;               // assert SS  
            else if (hit)
                ss_o <= 1'b0;               // hold SS    
            else
                ss_o <= 1'b1;               // deassert   
        end
    end
 
endmodule

tb/spi_slave_select_tb.v
`timescale 1ns / 1ps
//////////////////////////////////////////////////////////////////////////////////
// Company: 
// Engineer: 
// 
// Create Date: 20.01.2026 23:29:11
// Design Name: 
// Module Name: spi_slave_select_tb
// Project Name: 
// Target Devices: 
// Tool Versions: 
// Description: 
// 
// Dependencies: 
// 
// Revision:
// Revision 0.01 - File Created
// Additional Comments:
// 
//////////////////////////////////////////////////////////////////////////////////


module spi_slave_select_tb ();
    reg         PCLK;
    reg         PRESET_n;
    reg         mstr_i;
    reg         spiswai_i;
    reg  [1:0]  spi_mode_i;
    reg         send_data_i;
    reg  [15:0] BaudRateDivisor_i;
 
    wire        receive_data_o;
    wire        ss_o;
    wire        tip_o;
 
    spi_slave_select DUT (
        .PCLK             (PCLK),
        .PRESET_n         (PRESET_n),
        .mstr_i           (mstr_i),
        .spiswai_i        (spiswai_i),
        .spi_mode_i       (spi_mode_i),       
        .send_data_i      (send_data_i),
        .BaudRateDivisor_i(BaudRateDivisor_i),
        .receive_data_o   (receive_data_o),
        .ss_o             (ss_o),
        .tip_o            (tip_o)
    );
 
    initial PCLK = 1'b0;
    always  #5 PCLK = ~PCLK;
 
    task initialize;
        begin
            PRESET_n          = 1'b1;
            mstr_i            = 1'b1;
            spiswai_i         = 1'b0;
            spi_mode_i        = 2'b00;    // STOP - no run/wait
            send_data_i       = 1'b0;
            BaudRateDivisor_i = 16'd4;    // target = 4×16 = 64 clocks per frame
        end
    endtask
 
    task apply_reset;
        begin
            PRESET_n = 1'b0;
            repeat (5) @(posedge PCLK);
            @(negedge PCLK);              
            PRESET_n = 1'b1;
            $display("[%0t] RESET released", $time);
        end
    endtask
 
    // start_spi: configure master, SPI_RUN mode, wait enabled
    task start_spi;
        begin
            mstr_i     = 1'b1;
            spiswai_i  = 1'b0;
            spi_mode_i = 2'b10;           // RUN
            $display("[%0t] SPI START (spi_mode=RUN)", $time);
        end
    endtask
 
    // stop_spi: put SPI back to STOP mode
    task stop_spi;
        begin
            spi_mode_i = 2'b00;           // STOP
            $display("[%0t] SPI STOP", $time);
        end
    endtask
 
    // send_frame: pulse send_data_i for exactly one PCLK cycle.
    //   Drive send_data_i HIGH before the rising edge so the DUT
    //   samples it on the next posedge PCLK. (Bug fix vs original TB.)
    task send_frame;
        begin
            @(negedge PCLK);              // drive on falling edge ...
            send_data_i = 1'b1;
            @(negedge PCLK);              // ... hold for one full cycle ...
            send_data_i = 1'b0;
            $display("[%0t] send_data asserted (1-cycle pulse)", $time);
        end
    endtask
 
    // wait_frame_done: block until ss_o deasserts (frame over).
    //   Timeout after 10000 ns to prevent infinite hang.
    task wait_frame_done;
        integer timeout;
        begin
            timeout = 0;
            while (ss_o === 1'b0 && timeout < 10000) begin
                @(posedge PCLK);
                timeout = timeout + 20;
            end
            if (ss_o !== 1'b1)
                $display("[%0t] WARNING: wait_frame_done timed out!", $time);
            else
                $display("[%0t] Frame done: ss_o deasserted", $time);
        end
    endtask
 
    // test_no_enable: verify ss_o stays 1 when enable conditions not met
    task test_no_enable;
        begin
            $display("[%0t] TEST: no-enable (slave mode)", $time);
            mstr_i = 1'b0;                // slave mode → enable=0
            send_frame;
            repeat (10) @(posedge PCLK);
            if (ss_o !== 1'b1)
                $display("[%0t] FAIL: ss_o should be 1 in slave mode", $time);
            else
                $display("[%0t] PASS: ss_o=1 when mstr_i=0", $time);
            mstr_i = 1'b1;                // restore master mode
        end
    endtask
 
    // test_reset_mid_frame: assert reset while frame is running
    task test_reset_mid_frame;
        begin
            $display("[%0t] TEST: reset mid-frame", $time);
            send_frame;
            repeat (10) @(posedge PCLK);  // wait a few cycles into the frame
            PRESET_n = 1'b0;
            repeat (3) @(posedge PCLK);
            @(negedge PCLK);
            PRESET_n = 1'b1;
            repeat (5) @(posedge PCLK);
            if (ss_o !== 1'b1)
                $display("[%0t] FAIL: ss_o should be 1 after mid-frame reset",
                         $time);
            else
                $display("[%0t] PASS: ss_o=1 after mid-frame reset", $time);
        end
    endtask
 
    initial begin
        $dumpfile("spi_slave_select_tb.vcd");
        $dumpvars(0, spi_slave_select_tb);
 
        initialize;
        apply_reset;
        start_spi;
 
        // ---- Test 1: no-enable check ----
        test_no_enable;
 
        // ---- Test 2: normal frame 1 ----
        $display("[%0t] ===== Frame 1 =====", $time);
        send_frame;
        wait_frame_done;
        repeat (5) @(posedge PCLK);
 
        // ---- Test 3: normal frame 2 ----
        $display("[%0t] ===== Frame 2 =====", $time);
        send_frame;
        wait_frame_done;
        repeat (5) @(posedge PCLK);
 
        // ---- Test 4: reset mid-frame ----
        $display("[%0t] ===== Mid-frame reset =====", $time);
        test_reset_mid_frame;
        repeat (5) @(posedge PCLK);
 
        // ---- Test 5: spi_wait mode ----
        $display("[%0t] ===== SPI WAIT mode =====", $time);
        spi_mode_i = 2'b01;              // spi_wait
        send_frame;
        wait_frame_done;
        repeat (5) @(posedge PCLK);
 
        // ---- Test 6: stop mode ----
        stop_spi;
        repeat (10) @(posedge PCLK);
        if (ss_o !== 1'b1)
            $display("[%0t] FAIL: ss_o should be 1 after stop", $time);
        else
            $display("[%0t] PASS: ss_o=1 after stop", $time);
 
        $display("[%0t] Simulation complete", $time);
        $finish;
    end
 
    initial begin
        $monitor("[%0t] SS=%b TIP=%b RCV=%b count=%0d",
                 $time, ss_o, tip_o, receive_data_o,
                 DUT.count_s);
    end
 
endmodule

sim/spi_top.sim/sim_1/behav/xsim/spi_slave_select_tb.vcd
$date
   Sun Jun 14 17:32:50 2026
$end

$version
  2025.1.0
  $dumpfile ("spi_slave_select_tb.vcd") 
$end

$timescale
  1ps
$end

$scope module spi_slave_select_tb $end
$var reg 1 ! PCLK $end
$var reg 1 " PRESET_n $end
$var reg 1 # mstr_i $end
$var reg 1 $ spiswai_i $end
$var reg 2 % spi_mode_i [1:0] $end
$var reg 1 & send_data_i $end
$var reg 16 ' BaudRateDivisor_i [15:0] $end
$var wire 1 ( receive_data_o $end
$var wire 1 ) ss_o $end
$var wire 1 * tip_o $end
$scope module DUT $end
$var wire 1 + PCLK $end
$var wire 1 , PRESET_n $end
$var wire 1 - mstr_i $end
$var wire 1 . spiswai_i $end
$var wire 2 / spi_mode_i [1:0] $end
$var wire 1 0 send_data_i $end
$var wire 16 1 BaudRateDivisor_i [15:0] $end
$var reg 1 2 receive_data_o $end
$var reg 1 3 ss_o $end
$var wire 1 * tip_o $end
$var reg 16 4 count_s [15:0] $end
$var reg 1 5 rcv_s $end
$var wire 16 6 target_s [15:0] $end
$var wire 1 7 hit $end
$var wire 1 8 hit1 $end
$var wire 1 9 spi_run $end
$var wire 1 : spi_wait $end
$var wire 1 ; mode_ok $end
$var wire 1 < enable $end
$upscope $end
$scope task initialize $end
$upscope $end
$scope task apply_reset $end
$upscope $end
$scope task start_spi $end
$upscope $end
$scope task stop_spi $end
$upscope $end
$scope task send_frame $end
$upscope $end
$scope task wait_frame_done $end
$var integer 32 = timeout [31:0] $end
$upscope $end
$scope task test_no_enable $end
$upscope $end
$scope task test_reset_mid_frame $end
$upscope $end
$upscope $end
$enddefinitions $end

#0
$dumpvars
0!
0"
1#
0$
b0 %
0&
b100 '
0(
1)
0*
0+
0,
1-
0.
b0 /
00
b100 1
02
13
b1111111111111111 4
05
b100000 6
07
08
09
0:
0;
0<
bx =
$end

#5000
1!
1+

#10000
0!
0+

#15000
1!
1+

#20000
0!
0+

#25000
1!
1+

#30000
0!
0+

#35000
1!
1+

#40000
0!
0+

#45000
1!
1+

#50000
0!
1"
0#
b10 %
0+
1,
0-
b10 /
19
1;

#55000
1!
1+

#60000
0!
1&
0+
10

#65000
1!
1+

#70000
0!
0&
0+
00

#75000
1!
1+

#80000
0!
0+

#85000
1!
1+

#90000
0!
0+

#95000
1!
1+

#100000
0!
0+

#105000
1!
1+

#110000
0!
0+

#115000
1!
1+

#120000
0!
0+

#125000
1!
1+

#130000
0!
0+

#135000
1!
1+

#140000
0!
0+

#145000
1!
1+

#150000
0!
0+

#155000
1!
1+

#160000
0!
0+

#165000
1!
1#
1+
1-
1<

#170000
0!
1&
0+
10

#175000
1!
0)
1*
1+
03
b0 4
17

#180000
0!
0&
0+
00
b0 =

#185000
1!
1+
b1 4
b10100 =

#190000
0!
0+

#195000
1!
1+
b10 4
b101000 =

#200000
0!
0+

#205000
1!
1+
b11 4
b111100 =

#210000
0!
0+

#215000
1!
1+
b100 4
b1010000 =

#220000
0!
0+

#225000
1!
1+
b101 4
b1100100 =

#230000
0!
0+

#235000
1!
1+
b110 4
b1111000 =

#240000
0!
0+

#245000
1!
1+
b111 4
b10001100 =

#250000
0!
0+

#255000
1!
1+
b1000 4
b10100000 =

#260000
0!
0+

#265000
1!
1+
b1001 4
b10110100 =

#270000
0!
0+

#275000
1!
1+
b1010 4
b11001000 =

#280000
0!
0+

#285000
1!
1+
b1011 4
b11011100 =

#290000
0!
0+

#295000
1!
1+
b1100 4
b11110000 =

#300000
0!
0+

#305000
1!
1+
b1101 4
b100000100 =

#310000
0!
0+

#315000
1!
1+
b1110 4
b100011000 =

#320000
0!
0+

#325000
1!
1+
b1111 4
b100101100 =

#330000
0!
0+

#335000
1!
1+
b10000 4
b101000000 =

#340000
0!
0+

#345000
1!
1+
b10001 4
b101010100 =

#350000
0!
0+

#355000
1!
1+
b10010 4
b101101000 =

#360000
0!
0+

#365000
1!
1+
b10011 4
b101111100 =

#370000
0!
0+

#375000
1!
1+
b10100 4
b110010000 =

#380000
0!
0+

#385000
1!
1+
b10101 4
b110100100 =

#390000
0!
0+

#395000
1!
1+
b10110 4
b110111000 =

#400000
0!
0+

#405000
1!
1+
b10111 4
b111001100 =

#410000
0!
0+

#415000
1!
1+
b11000 4
b111100000 =

#420000
0!
0+

#425000
1!
1+
b11001 4
b111110100 =

#430000
0!
0+

#435000
1!
1+
b11010 4
b1000001000 =

#440000
0!
0+

#445000
1!
1+
b11011 4
b1000011100 =

#450000
0!
0+

#455000
1!
1+
b11100 4
b1000110000 =

#460000
0!
0+

#465000
1!
1+
b11101 4
b1001000100 =

#470000
0!
0+

#475000
1!
1+
b11110 4
b1001011000 =

#480000
0!
0+

#485000
1!
1+
b11111 4
18
b1001101100 =

#490000
0!
0+

#495000
1!
1+
b100000 4
15
07
08
b1010000000 =

#500000
0!
0+

#505000
1!
1(
1)
0*
1+
12
13
b1111111111111111 4
05
b1010010100 =

#510000
0!
0+

#515000
1!
0(
1+
02
b1010101000 =

#520000
0!
0+

#525000
1!
1+

#530000
0!
0+

#535000
1!
1+

#540000
0!
0+

#545000
1!
1+

#550000
0!
0+

#555000
1!
1+

#560000
0!
0+

#565000
1!
1+

#570000
0!
1&
0+
10

#575000
1!
0)
1*
1+
03
b0 4
17

#580000
0!
0&
0+
00
b0 =

#585000
1!
1+
b1 4
b10100 =

#590000
0!
0+

#595000
1!
1+
b10 4
b101000 =

#600000
0!
0+

#605000
1!
1+
b11 4
b111100 =

#610000
0!
0+

#615000
1!
1+
b100 4
b1010000 =

#620000
0!
0+

#625000
1!
1+
b101 4
b1100100 =

#630000
0!
0+

#635000
1!
1+
b110 4
b1111000 =

#640000
0!
0+

#645000
1!
1+
b111 4
b10001100 =

#650000
0!
0+

#655000
1!
1+
b1000 4
b10100000 =

#660000
0!
0+

#665000
1!
1+
b1001 4
b10110100 =

#670000
0!
0+

#675000
1!
1+
b1010 4
b11001000 =

#680000
0!
0+

#685000
1!
1+
b1011 4
b11011100 =

#690000
0!
0+

#695000
1!
1+
b1100 4
b11110000 =

#700000
0!
0+

#705000
1!
1+
b1101 4
b100000100 =

#710000
0!
0+

#715000
1!
1+
b1110 4
b100011000 =

#720000
0!
0+

#725000
1!
1+
b1111 4
b100101100 =

#730000
0!
0+

#735000
1!
1+
b10000 4
b101000000 =

#740000
0!
0+

#745000
1!
1+
b10001 4
b101010100 =

#750000
0!
0+

#755000
1!
1+
b10010 4
b101101000 =

#760000
0!
0+

#765000
1!
1+
b10011 4
b101111100 =

#770000
0!
0+

#775000
1!
1+
b10100 4
b110010000 =

#780000
0!
0+

#785000
1!
1+
b10101 4
b110100100 =

#790000
0!
0+

#795000
1!
1+
b10110 4
b110111000 =

#800000
0!
0+

#805000
1!
1+
b10111 4
b111001100 =

#810000
0!
0+

#815000
1!
1+
b11000 4
b111100000 =

#820000
0!
0+

#825000
1!
1+
b11001 4
b111110100 =

#830000
0!
0+

#835000
1!
1+
b11010 4
b1000001000 =

#840000
0!
0+

#845000
1!
1+
b11011 4
b1000011100 =

#850000
0!
0+

#855000
1!
1+
b11100 4
b1000110000 =

#860000
0!
0+

#865000
1!
1+
b11101 4
b1001000100 =

#870000
0!
0+

#875000
1!
1+
b11110 4
b1001011000 =

#880000
0!
0+

#885000
1!
1+
b11111 4
18
b1001101100 =

#890000
0!
0+

#895000
1!
1+
b100000 4
15
07
08
b1010000000 =

#900000
0!
0+

#905000
1!
1(
1)
0*
1+
12
13
b1111111111111111 4
05
b1010010100 =

#910000
0!
0+

#915000
1!
0(
1+
02
b1010101000 =

#920000
0!
0+

#925000
1!
1+

#930000
0!
0+

#935000
1!
1+

#940000
0!
0+

#945000
1!
1+

#950000
0!
0+

#955000
1!
1+

#960000
0!
0+

#965000
1!
1+

#970000
0!
1&
0+
10

#975000
1!
0)
1*
1+
03
b0 4
17

#980000
0!
0&
0+
00

#985000
1!
1+
b1 4

#990000
0!
0+

#995000
1!
1+
b10 4

#1000000
0!
0+

#1005000
1!
1+
b11 4

#1010000
0!
0+

#1015000
1!
1+
b100 4

#1020000
0!
0+

#1025000
1!
1+
b101 4

#1030000
0!
0+

#1035000
1!
1+
b110 4

#1040000
0!
0+

#1045000
1!
1+
b111 4

#1050000
0!
0+

#1055000
1!
1+
b1000 4

#1060000
0!
0+

#1065000
1!
1+
b1001 4

#1070000
0!
0+

#1075000
1!
0"
1)
0*
1+
0,
13
b1111111111111111 4
07

#1080000
0!
0+

#1085000
1!
1+

#1090000
0!
0+

#1095000
1!
1+

#1100000
0!
0+

#1105000
1!
1+

#1110000
0!
1"
0+
1,

#1115000
1!
1+

#1120000
0!
0+

#1125000
1!
1+

#1130000
0!
0+

#1135000
1!
1+

#1140000
0!
0+

#1145000
1!
1+

#1150000
0!
0+

#1155000
1!
1+

#1160000
0!
0+

#1165000
1!
1+

#1170000
0!
0+

#1175000
1!
1+

#1180000
0!
0+

#1185000
1!
1+

#1190000
0!
0+

#1195000
1!
1+

#1200000
0!
0+

#1205000
1!
b1 %
1+
b1 /
09
1:

#1210000
0!
1&
0+
10

#1215000
1!
0)
1*
1+
03
b0 4
17

#1220000
0!
0&
0+
00
b0 =

#1225000
1!
1+
b1 4
b10100 =

#1230000
0!
0+

#1235000
1!
1+
b10 4
b101000 =

#1240000
0!
0+

#1245000
1!
1+
b11 4
b111100 =

#1250000
0!
0+

#1255000
1!
1+
b100 4
b1010000 =

#1260000
0!
0+

#1265000
1!
1+
b101 4
b1100100 =

#1270000
0!
0+

#1275000
1!
1+
b110 4
b1111000 =

#1280000
0!
0+

#1285000
1!
1+
b111 4
b10001100 =

#1290000
0!
0+

#1295000
1!
1+
b1000 4
b10100000 =

#1300000
0!
0+

#1305000
1!
1+
b1001 4
b10110100 =

#1310000
0!
0+

#1315000
1!
1+
b1010 4
b11001000 =

#1320000
0!
0+

#1325000
1!
1+
b1011 4
b11011100 =

#1330000
0!
0+

#1335000
1!
1+
b1100 4
b11110000 =

#1340000
0!
0+

#1345000
1!
1+
b1101 4
b100000100 =

#1350000
0!
0+

#1355000
1!
1+
b1110 4
b100011000 =

#1360000
0!
0+

#1365000
1!
1+
b1111 4
b100101100 =

#1370000
0!
0+

#1375000
1!
1+
b10000 4
b101000000 =

#1380000
0!
0+

#1385000
1!
1+
b10001 4
b101010100 =

#1390000
0!
0+

#1395000
1!
1+
b10010 4
b101101000 =

#1400000
0!
0+

#1405000
1!
1+
b10011 4
b101111100 =

#1410000
0!
0+

#1415000
1!
1+
b10100 4
b110010000 =

#1420000
0!
0+

#1425000
1!
1+
b10101 4
b110100100 =

#1430000
0!
0+

#1435000
1!
1+
b10110 4
b110111000 =

#1440000
0!
0+

#1445000
1!
1+
b10111 4
b111001100 =

#1450000
0!
0+

#1455000
1!
1+
b11000 4
b111100000 =

#1460000
0!
0+

#1465000
1!
1+
b11001 4
b111110100 =

#1470000
0!
0+

#1475000
1!
1+
b11010 4
b1000001000 =

#1480000
0!
0+

#1485000
1!
1+
b11011 4
b1000011100 =

#1490000
0!
0+

#1495000
1!
1+
b11100 4
b1000110000 =

#1500000
0!
0+

#1505000
1!
1+
b11101 4
b1001000100 =

#1510000
0!
0+

#1515000
1!
1+
b11110 4
b1001011000 =

#1520000
0!
0+

#1525000
1!
1+
b11111 4
18
b1001101100 =

#1530000
0!
0+

#1535000
1!
1+
b100000 4
15
07
08
b1010000000 =

#1540000
0!
0+

#1545000
1!
1(
1)
0*
1+
12
13
b1111111111111111 4
05
b1010010100 =

#1550000
0!
0+

#1555000
1!
0(
1+
02
b1010101000 =

#1560000
0!
0+

#1565000
1!
1+

#1570000
0!
0+

#1575000
1!
1+

#1580000
0!
0+

#1585000
1!
1+

#1590000
0!
0+

#1595000
1!
1+

#1600000
0!
0+

#1605000
1!
b0 %
1+
b0 /
0:
0;
0<

